{"93":{"maxcombo":352,"statistics":{"count_100":32,"count_300":630,"count_50":7,"count_geki":1000,"count_katu":203,"count_miss":37},"user_id":25824877,"score_id":543708748,"rank":"A","pp":221.705},"94":{"maxcombo":771,"statistics":{"count_100":43,"count_300":632,"count_50":4,"count_geki":1027,"count_katu":183,"count_miss":20},"user_id":12410438,"score_id":543734034,"rank":"A","pp":242.999},"95":{"maxcombo":1571,"statistics":{"count_100":40,"count_300":579,"count_50":0,"count_geki":1126,"count_katu":144,"count_miss":20},"user_id":18163260,"score_id":544918715,"rank":"S","pp":268.732},"96":{"maxcombo":1576,"statistics":{"count_100":23,"count_300":618,"count_50":2,"count_geki":1117,"count_katu":135,"count_miss":14},"user_id":21339826,"score_id":543720028,"rank":"S","pp":287.377},"97":{"maxcombo":1515,"statistics":{"count_100":10,"count_300":600,"count_50":5,"count_geki":1168,"count_katu":121,"count_miss":5},"user_id":17271908,"score_id":544948377,"rank":"S","pp":311.355},"98":{"maxcombo":1669,"statistics":{"count_100":1,"count_300":442,"count_50":3,"count_geki":1374,"count_katu":83,"count_miss":6},"user_id":19650229,"score_id":544517725,"rank":"S","pp":345.481},"99":{"maxcombo":1284,"statistics":{"count_100":3,"count_300":526,"count_50":1,"count_geki":1345,"count_katu":27,"count_miss":7},"user_id":26499038,"score_id":543766054,"rank":"S","pp":362.063},"100":{"maxcombo":2487,"statistics":{"count_100":0,"count_300":142,"count_50":0,"count_geki":1767,"count_katu":0,"count_miss":0},"user_id":18236316,"score_id":544251565,"rank":"X","pp":410.535},"99.8":{"maxcombo":2479,"statistics":{"count_100":0,"count_300":402,"count_50":0,"count_geki":1496,"count_katu":11,"count_miss":0},"user_id":14241467,"score_id":543858546,"rank":"S","pp":388.105},"99.2":{"maxcombo":1701,"statistics":{"count_100":2,"count_300":357,"count_50":3,"count_geki":1519,"count_katu":27,"count_miss":1},"user_id":11928361,"score_id":544818972,"rank":"S","pp":379.195},"98.9":{"maxcombo":1286,"statistics":{"count_100":8,"count_300":383,"count_50":0,"count_geki":1482,"count_katu":33,"count_miss":3},"user_id":28429995,"score_id":544681809,"rank":"S","pp":370.973},"99.5":{"maxcombo":1648,"statistics":{"count_100":0,"count_300":370,"count_50":0,"count_geki":1520,"count_katu":16,"count_miss":3},"user_id":15532380,"score_id":544009180,"rank":"S","pp":384.94},"99.1":{"maxcombo":1579,"statistics":{"count_100":2,"count_300":422,"count_50":1,"count_geki":1446,"count_katu":35,"count_miss":3},"user_id":19251539,"score_id":544281851,"rank":"S","pp":371.076},"98.2":{"maxcombo":2383,"statistics":{"count_100":19,"count_300":409,"count_50":0,"count_geki":1432,"count_katu":43,"count_miss":6},"user_id":27904863,"score_id":544176944,"rank":"S","pp":353.428},"98.5":{"maxcombo":1622,"statistics":{"count_100":4,"count_300":431,"count_50":2,"count_geki":1412,"count_katu":55,"count_miss":5},"user_id":13859109,"score_id":543983378,"rank":"S","pp":357.556},"98.8":{"maxcombo":1579,"statistics":{"count_100":2,"count_300":380,"count_50":0,"count_geki":1483,"count_katu":34,"count_miss":10},"user_id":16787675,"score_id":543810715,"rank":"S","pp":367.602},"98.3":{"maxcombo":1701,"statistics":{"count_100":9,"count_300":353,"count_50":1,"count_geki":1488,"count_katu":49,"count_miss":9},"user_id":13582598,"score_id":544310551,"rank":"S","pp":358.141},"98.6":{"maxcombo":2044,"statistics":{"count_100":0,"count_300":605,"count_50":0,"count_geki":1232,"count_katu":69,"count_miss":3},"user_id":29568704,"score_id":544809301,"rank":"S","pp":346.892},"99.7":{"maxcombo":2490,"statistics":{"count_100":0,"count_300":307,"count_50":0,"count_geki":1585,"count_katu":17,"count_miss":0},"user_id":30557499,"score_id":543691326,"rank":"S","pp":392.164},"99.6":{"maxcombo":2444,"statistics":{"count_100":3,"count_300":309,"count_50":1,"count_geki":1584,"count_katu":12,"count_miss":0},"user_id":24548857,"score_id":544497367,"rank":"S","pp":390.892},"98.4":{"maxcombo":1917,"statistics":{"count_100":3,"count_300":583,"count_50":1,"count_geki":1247,"count_katu":71,"count_miss":4},"user_id":22491203,"score_id":544457860,"rank":"S","pp":343.28},"98.1":{"maxcombo":1459,"statistics":{"count_100":7,"count_300":614,"count_50":0,"count_geki":1196,"count_katu":91,"count_miss":1},"user_id":30220646,"score_id":545128282,"rank":"S","pp":334.095},"98.7":{"maxcombo":2164,"statistics":{"count_100":7,"count_300":561,"count_50":0,"count_geki":1291,"count_katu":47,"count_miss":3},"user_id":25675477,"score_id":544143710,"rank":"S","pp":353.704},"97.8":{"maxcombo":1601,"statistics":{"count_100":8,"count_300":510,"count_50":2,"count_geki":1300,"count_katu":83,"count_miss":6},"user_id":32408892,"score_id":545017453,"rank":"S","pp":336.434},"97.5":{"maxcombo":1302,"statistics":{"count_100":11,"count_300":671,"count_50":2,"count_geki":1123,"count_katu":95,"count_miss":7},"user_id":29394008,"score_id":545048380,"rank":"S","pp":317.031},"97.7":{"maxcombo":1575,"statistics":{"count_100":6,"count_300":631,"count_50":1,"count_geki":1170,"count_katu":94,"count_miss":7},"user_id":28949450,"score_id":543841382,"rank":"S","pp":324.909},"97.9":{"maxcombo":1742,"statistics":{"count_100":13,"count_300":542,"count_50":0,"count_geki":1270,"count_katu":79,"count_miss":5},"user_id":19901165,"score_id":543778993,"rank":"S","pp":335.058},"99.3":{"maxcombo":1087,"statistics":{"count_100":1,"count_300":245,"count_50":0,"count_geki":1637,"count_katu":20,"count_miss":6},"user_id":29906286,"score_id":544517693,"rank":"S","pp":387.83},"97.6":{"maxcombo":2382,"statistics":{"count_100":12,"count_300":621,"count_50":1,"count_geki":1178,"count_katu":92,"count_miss":5},"user_id":20964356,"score_id":544241305,"rank":"S","pp":324.084},"97.4":{"maxcombo":1569,"statistics":{"count_100":16,"count_300":592,"count_50":2,"count_geki":1195,"count_katu":102,"count_miss":2},"user_id":20763941,"score_id":543910547,"rank":"S","pp":321.297},"96.7":{"maxcombo":1875,"statistics":{"count_100":19,"count_300":581,"count_50":2,"count_geki":1176,"count_katu":125,"count_miss":6},"user_id":32269569,"score_id":544890206,"rank":"S","pp":305.885},"97.1":{"maxcombo":1689,"statistics":{"count_100":5,"count_300":590,"count_50":1,"count_geki":1187,"count_katu":115,"count_miss":11},"user_id":19477584,"score_id":544428954,"rank":"S","pp":315.415},"96.4":{"maxcombo":1212,"statistics":{"count_100":17,"count_300":540,"count_50":1,"count_geki":1206,"count_katu":134,"count_miss":11},"user_id":7230851,"score_id":543792413,"rank":"S","pp":301.929},"96.9":{"maxcombo":1582,"statistics":{"count_100":22,"count_300":660,"count_50":3,"count_geki":1117,"count_katu":98,"count_miss":9},"user_id":23221370,"score_id":543837698,"rank":"S","pp":305.094},"97.3":{"maxcombo":1639,"statistics":{"count_100":16,"count_300":520,"count_50":2,"count_geki":1271,"count_katu":94,"count_miss":6},"user_id":26162579,"score_id":544249671,"rank":"S","pp":325.15},"96.6":{"maxcombo":1695,"statistics":{"count_100":21,"count_300":600,"count_50":5,"count_geki":1164,"count_katu":109,"count_miss":10},"user_id":14684909,"score_id":543723211,"rank":"S","pp":302.48},"96.2":{"maxcombo":1578,"statistics":{"count_100":27,"count_300":587,"count_50":1,"count_geki":1165,"count_katu":114,"count_miss":15},"user_id":4397151,"score_id":543691913,"rank":"S","pp":294.98},"99.4":{"maxcombo":2441,"statistics":{"count_100":1,"count_300":491,"count_50":0,"count_geki":1387,"count_katu":30,"count_miss":0},"user_id":22199280,"score_id":543710042,"rank":"S","pp":373.381},"96.1":{"maxcombo":1693,"statistics":{"count_100":33,"count_300":545,"count_50":4,"count_geki":1196,"count_katu":123,"count_miss":8},"user_id":15622311,"score_id":544529580,"rank":"S","pp":294.533},"97.2":{"maxcombo":1289,"statistics":{"count_100":8,"count_300":529,"count_50":2,"count_geki":1275,"count_katu":74,"count_miss":21},"user_id":10903923,"score_id":543950249,"rank":"S","pp":322.329},"96.5":{"maxcombo":2311,"statistics":{"count_100":17,"count_300":568,"count_50":0,"count_geki":1179,"count_katu":136,"count_miss":9},"user_id":14040274,"score_id":544631485,"rank":"S","pp":302.307},"95.2":{"maxcombo":1127,"statistics":{"count_100":32,"count_300":569,"count_50":2,"count_geki":1144,"count_katu":141,"count_miss":21},"user_id":27640326,"score_id":543991764,"rank":"S","pp":273.754},"96.3":{"maxcombo":1302,"statistics":{"count_100":12,"count_300":577,"count_50":3,"count_geki":1170,"count_katu":133,"count_miss":14},"user_id":20293574,"score_id":544029500,"rank":"S","pp":298.42},"95.8":{"maxcombo":1118,"statistics":{"count_100":20,"count_300":587,"count_50":4,"count_geki":1149,"count_katu":129,"count_miss":20},"user_id":23161975,"score_id":544413979,"rank":"S","pp":285.795},"95.1":{"maxcombo":1595,"statistics":{"count_100":28,"count_300":689,"count_50":4,"count_geki":1004,"count_katu":169,"count_miss":15},"user_id":26162501,"score_id":544280572,"rank":"S","pp":261.714},"95.4":{"maxcombo":1132,"statistics":{"count_100":25,"count_300":653,"count_50":3,"count_geki":1067,"count_katu":141,"count_miss":20},"user_id":33834721,"score_id":544707778,"rank":"S","pp":273.445},"96.8":{"maxcombo":1445,"statistics":{"count_100":9,"count_300":692,"count_50":2,"count_geki":1069,"count_katu":126,"count_miss":11},"user_id":25003909,"score_id":543713289,"rank":"S","pp":299.899},"95.6":{"maxcombo":1157,"statistics":{"count_100":19,"count_300":594,"count_50":3,"count_geki":1124,"count_katu":151,"count_miss":18},"user_id":16282692,"score_id":544226837,"rank":"S","pp":280.118},"95.3":{"maxcombo":1227,"statistics":{"count_100":18,"count_300":644,"count_50":8,"count_geki":1057,"count_katu":168,"count_miss":14},"user_id":21790877,"score_id":543972599,"rank":"S","pp":270.176},"94.7":{"maxcombo":1057,"statistics":{"count_100":17,"count_300":636,"count_50":3,"count_geki":1046,"count_katu":180,"count_miss":27},"user_id":16901625,"score_id":543968680,"rank":"A","pp":256.863},"93.4":{"maxcombo":1190,"statistics":{"count_100":48,"count_300":618,"count_50":5,"count_geki":1012,"count_katu":206,"count_miss":20},"user_id":31491582,"score_id":543836625,"rank":"A","pp":229.754},"95.9":{"maxcombo":834,"statistics":{"count_100":15,"count_300":596,"count_50":3,"count_geki":1131,"count_katu":148,"count_miss":16},"user_id":17194567,"score_id":543700951,"rank":"S","pp":286.448},"93.9":{"maxcombo":462,"statistics":{"count_100":36,"count_300":607,"count_50":5,"count_geki":1049,"count_katu":186,"count_miss":26},"user_id":20426897,"score_id":543778278,"rank":"A","pp":241.245},"94.4":{"maxcombo":810,"statistics":{"count_100":39,"count_300":678,"count_50":2,"count_geki":1007,"count_katu":158,"count_miss":25},"user_id":30527099,"score_id":544101837,"rank":"A","pp":249.535},"95.5":{"maxcombo":1574,"statistics":{"count_100":30,"count_300":585,"count_50":4,"count_geki":1135,"count_katu":140,"count_miss":15},"user_id":32529741,"score_id":544085984,"rank":"S","pp":279.327},"94.2":{"maxcombo":1173,"statistics":{"count_100":28,"count_300":598,"count_50":5,"count_geki":1060,"count_katu":197,"count_miss":21},"user_id":25669035,"score_id":543829276,"rank":"A","pp":248.882},"93.7":{"maxcombo":1318,"statistics":{"count_100":44,"count_300":652,"count_50":5,"count_geki":986,"count_katu":203,"count_miss":19},"user_id":27139986,"score_id":544166670,"rank":"A","pp":232.782},"95.7":{"maxcombo":690,"statistics":{"count_100":18,"count_300":627,"count_50":3,"count_geki":1101,"count_katu":141,"count_miss":19},"user_id":31964935,"score_id":544191046,"rank":"S","pp":281.632},"91.2":{"maxcombo":982,"statistics":{"count_100":52,"count_300":587,"count_50":6,"count_geki":990,"count_katu":219,"count_miss":55},"user_id":30698721,"score_id":544321519,"rank":"A","pp":184.035},"93.8":{"maxcombo":796,"statistics":{"count_100":42,"count_300":642,"count_50":7,"count_geki":1020,"count_katu":173,"count_miss":25},"user_id":28635927,"score_id":544884983,"rank":"A","pp":238.905},"94.9":{"maxcombo":1022,"statistics":{"count_100":26,"count_300":644,"count_50":6,"count_geki":1062,"count_katu":146,"count_miss":25},"user_id":10462777,"score_id":543785275,"rank":"A","pp":262.952},"94.8":{"maxcombo":563,"statistics":{"count_100":30,"count_300":614,"count_50":16,"count_geki":1099,"count_katu":127,"count_miss":23},"user_id":5997795,"score_id":545057803,"rank":"A","pp":262.746},"94.1":{"maxcombo":441,"statistics":{"count_100":28,"count_300":588,"count_50":3,"count_geki":1077,"count_katu":183,"count_miss":30},"user_id":2077540,"score_id":543764479,"rank":"A","pp":247.299},"94.6":{"maxcombo":1240,"statistics":{"count_100":29,"count_300":568,"count_50":8,"count_geki":1123,"count_katu":158,"count_miss":23},"user_id":25990095,"score_id":544583024,"rank":"A","pp":261.301},"93.2":{"maxcombo":1124,"statistics":{"count_100":45,"count_300":623,"count_50":11,"count_geki":1013,"count_katu":191,"count_miss":26},"user_id":20328919,"score_id":544314936,"rank":"A","pp":225.695},"94.3":{"maxcombo":928,"statistics":{"count_100":30,"count_300":585,"count_50":8,"count_geki":1061,"count_katu":215,"count_miss":10},"user_id":30874595,"score_id":544113104,"rank":"A","pp":250.155},"94.5":{"maxcombo":440,"statistics":{"count_100":16,"count_300":587,"count_50":10,"count_geki":1116,"count_katu":142,"count_miss":38},"user_id":31429634,"score_id":544564046,"rank":"A","pp":258.067},"93.6":{"maxcombo":595,"statistics":{"count_100":36,"count_300":622,"count_50":11,"count_geki":1016,"count_katu":204,"count_miss":20},"user_id":31196517,"score_id":543906073,"rank":"A","pp":233.814}}