{"99.1":{"maxcombo":1125,"statistics":{"count_100":1,"count_300":226,"count_50":0,"count_geki":502,"count_katu":18,"count_miss":0},"user_id":27492183,"score_id":522847952,"rank":"S","pp":66.6042},"98.3":{"maxcombo":1135,"statistics":{"count_100":2,"count_300":239,"count_50":0,"count_geki":472,"count_katu":34,"count_miss":0},"user_id":28272202,"score_id":526281613,"rank":"S","pp":62.6966},"93.4":{"maxcombo":271,"statistics":{"count_100":13,"count_300":276,"count_50":5,"count_geki":358,"count_katu":88,"count_miss":7},"user_id":33017534,"score_id":539705412,"rank":"A","pp":41.1563}}