{"95.2":{"maxcombo":1485,"statistics":{"count_100":141,"count_300":1344,"count_50":0,"count_geki":0,"count_katu":0,"count_miss":0},"user_id":26851066,"score_id":179338975,"rank":"S","pp":224.052},"96.4":{"maxcombo":704,"statistics":{"count_100":98,"count_300":1384,"count_50":0,"count_geki":9,"count_katu":0,"count_miss":3},"user_id":11594132,"score_id":173749173,"rank":"A","pp":231.969},"98.4":{"maxcombo":653,"statistics":{"count_100":41,"count_300":1441,"count_50":0,"count_geki":9,"count_katu":0,"count_miss":3},"user_id":7344872,"score_id":167224636,"rank":"A","pp":254.665},"96.3":{"maxcombo":487,"statistics":{"count_100":97,"count_300":1382,"count_50":0,"count_geki":6,"count_katu":1,"count_miss":6},"user_id":12148373,"score_id":167185018,"rank":"A","pp":224.746}}