{"98":{"maxcombo":188,"statistics":{"count_100":3,"count_300":329,"count_50":0,"count_geki":0,"count_katu":0,"count_miss":5},"user_id":10243433,"score_id":179955974,"rank":"A","pp":107.698},"100":{"maxcombo":337,"statistics":{"count_100":0,"count_300":337,"count_50":0,"count_geki":2,"count_katu":0,"count_miss":0},"user_id":27613947,"score_id":179922523,"rank":"X","pp":133.008},"99.5":{"maxcombo":337,"statistics":{"count_100":3,"count_300":334,"count_50":0,"count_geki":15,"count_katu":0,"count_miss":0},"user_id":11035895,"score_id":179927354,"rank":"S","pp":130.405},"97.9":{"maxcombo":337,"statistics":{"count_100":14,"count_300":323,"count_50":0,"count_geki":0,"count_katu":0,"count_miss":0},"user_id":12250316,"score_id":179916511,"rank":"S","pp":121.399},"99.1":{"maxcombo":337,"statistics":{"count_100":6,"count_300":331,"count_50":0,"count_geki":0,"count_katu":0,"count_miss":0},"user_id":10256562,"score_id":179916409,"rank":"S","pp":127.867},"99.7":{"maxcombo":337,"statistics":{"count_100":2,"count_300":335,"count_50":0,"count_geki":1,"count_katu":0,"count_miss":0},"user_id":3457063,"score_id":179962182,"rank":"S","pp":131.266},"97.7":{"maxcombo":222,"statistics":{"count_100":11,"count_300":324,"count_50":0,"count_geki":1,"count_katu":0,"count_miss":2},"user_id":18835948,"score_id":179914461,"rank":"A","pp":114.525},"95.5":{"maxcombo":337,"statistics":{"count_100":30,"count_300":307,"count_50":0,"count_geki":15,"count_katu":0,"count_miss":0},"user_id":13545955,"score_id":179929407,"rank":"S","pp":109.671},"96.2":{"maxcombo":337,"statistics":{"count_100":25,"count_300":312,"count_50":0,"count_geki":0,"count_katu":0,"count_miss":0},"user_id":29946528,"score_id":179936693,"rank":"S","pp":113.173},"95.4":{"maxcombo":226,"statistics":{"count_100":23,"count_300":310,"count_50":0,"count_geki":8,"count_katu":0,"count_miss":4},"user_id":15501289,"score_id":179911345,"rank":"A","pp":97.7445},"94.8":{"maxcombo":337,"statistics":{"count_100":35,"count_300":302,"count_50":0,"count_geki":3,"count_katu":0,"count_miss":0},"user_id":25378633,"score_id":179920964,"rank":"A","pp":106.309},"92.5":{"maxcombo":219,"statistics":{"count_100":44,"count_300":290,"count_50":0,"count_geki":10,"count_katu":0,"count_miss":3},"user_id":15649946,"score_id":179904262,"rank":"B","pp":88.8581},"97.3":{"maxcombo":337,"statistics":{"count_100":18,"count_300":319,"count_50":0,"count_geki":3,"count_katu":0,"count_miss":0},"user_id":11622358,"score_id":179955182,"rank":"S","pp":118.321},"92.1":{"maxcombo":189,"statistics":{"count_100":49,"count_300":286,"count_50":0,"count_geki":9,"count_katu":0,"count_miss":2},"user_id":29871097,"score_id":179956748,"rank":"B","pp":89.7852},"95.8":{"maxcombo":200,"statistics":{"count_100":12,"count_300":317,"count_50":0,"count_geki":0,"count_katu":0,"count_miss":8},"user_id":17096206,"score_id":179901155,"rank":"A","pp":89.9984},"85.7":{"maxcombo":153,"statistics":{"count_100":52,"count_300":263,"count_50":0,"count_geki":0,"count_katu":0,"count_miss":22},"user_id":11299562,"score_id":179962702,"rank":"C","pp":37.5081}}